{
  "project_info": {
    "project_number": "38335461579",
    "project_id": "lottery-5",
    "storage_bucket": "lottery-5.appspot.com"
  },
  "client": [
    {
      "client_info": {
        "mobilesdk_app_id": "1:38335461579:android:c98df87510f2473cdf434e",
        "android_client_info": {
          "package_name": "com.shockwave.m99vin"
        }
      },
      "oauth_client": [
        {
          "client_id": "38335461579-q6nscj518qj0jql67ci0tpegc1qt7ord.apps.googleusercontent.com",
          "client_type": 3
        }
      ],
      "api_key": [
        {
          "current_key": "AIzaSyDSJaA_IKDk2hpBVeQdb051GAUhndXs1hQ"
        }
      ],
      "services": {
        "appinvite_service": {
          "other_platform_oauth_client": [
            {
              "client_id": "38335461579-q6nscj518qj0jql67ci0tpegc1qt7ord.apps.googleusercontent.com",
              "client_type": 3
            }
          ]
        }
      }
    }
  ],
  "configuration_version": "1"
}